centraltechpack/__init__.py
centraltechpack/cli.py
centraltechpack/datasets/__init__.py
centraltechpack/datasets/loader.py
centraltechpack/datasets/registry.py
centraltechpack/datasets/data/medicine/diabete.csv
centraltechpack/notebooks/__init__.py
centraltechpack/notebooks/exporter.py
centraltechpack/notebooks/registry.py
centraltechpack/notebooks/content/ml_engineer_cheatsheet.ipynb
centraltechpack-0.1.1.dist-info/licenses/LICENSE
centraltechpack-0.1.1.dist-info/METADATA
centraltechpack-0.1.1.dist-info/WHEEL
centraltechpack-0.1.1.dist-info/entry_points.txt
centraltechpack-0.1.1.dist-info/top_level.txt
centraltechpack-0.1.1.dist-info/RECORD
