Metadata-Version: 2.4
Name: CentralTechPack
Version: 0.1.1
Summary: Datasets pack for CentraleTech trainings (medicine, astro, etc.)
Author-email: DutyRisto <deconquestdelfa@gmail.com>
License: MIT License
Project-URL: Homepage, https://github.com/DutyRisto/CentraleTechPack
Project-URL: Issues, https://github.com/DutyRisto/CentraleTechPack/issues
Keywords: dataset,training,education,data
Classifier: Programming Language :: Python :: 3
Classifier: License :: OSI Approved :: MIT License
Classifier: Operating System :: OS Independent
Requires-Python: >=3.9
License-File: LICENSE
Dynamic: license-file
